textual_hires_canvas/__init__.py
textual_hires_canvas/canvas.py
textual_hires_canvas/demo.py
textual_hires_canvas/hires.py
textual_hires_canvas/py.typed
textual_hires_canvas-0.14.0.dist-info/METADATA
textual_hires_canvas-0.14.0.dist-info/WHEEL
textual_hires_canvas-0.14.0.dist-info/entry_points.txt
textual_hires_canvas-0.14.0.dist-info/licenses/LICENSE
textual_hires_canvas-0.14.0.dist-info/RECORD
