Metadata-Version: 2.4
Name: textual-hires-canvas
Version: 0.14.0
Summary: High-resolution drawing canvas for Textual apps
Project-URL: Homepage, https://github.com/davidfokkema/textual-hires-canvas
Project-URL: Repository, https://github.com/davidfokkema/textual-hires-canvas.git
Project-URL: Issues, https://github.com/davidfokkema/textual-hires-canvas/issues
Project-URL: Changelog, https://github.com/davidfokkema/textual-hires-canvas/blob/main/CHANGELOG.md
Author-email: David Fokkema <davidfokkema@icloud.com>
License-Expression: MIT
License-File: LICENSE
Requires-Python: >=3.10
Requires-Dist: numpy>=2.2.1
Requires-Dist: textual>=6.2.0
